glyphviewer/__init__.py
glyphviewer/blocks.py
glyphviewer/glyphviewer.py
glyphviewer/urls.py
glyphviewer/views.py
glyphviewer/static/glyphviewer/fonts/FreeMono.woff
glyphviewer/static/glyphviewer/fonts/FreeMonoBold.woff
glyphviewer/static/glyphviewer/fonts/FreeMonoBoldOblique.woff
glyphviewer/static/glyphviewer/fonts/FreeMonoOblique.woff
glyphviewer/static/glyphviewer/fonts/FreeSans.woff
glyphviewer/static/glyphviewer/fonts/FreeSansBold.woff
glyphviewer/static/glyphviewer/fonts/FreeSansBoldOblique.woff
glyphviewer/static/glyphviewer/fonts/FreeSansOblique.woff
glyphviewer/static/glyphviewer/fonts/FreeSerif.woff
glyphviewer/static/glyphviewer/fonts/FreeSerifBold.woff
glyphviewer/static/glyphviewer/fonts/FreeSerifBoldItalic.woff
glyphviewer/static/glyphviewer/fonts/FreeSerifItalic.woff
glyphviewer/templates/glyphviewer/doc.html
glyphviewer/templates/glyphviewer/index.html
glyphviewer/templates/glyphviewer/showheader.html
glyphviewer/templatetags/__init__.py
glyphviewer/templatetags/glyphtable.py
glyphviewer-0.8.1.dist-info/LICENSE.txt
glyphviewer-0.8.1.dist-info/METADATA
glyphviewer-0.8.1.dist-info/WHEEL
glyphviewer-0.8.1.dist-info/top_level.txt
glyphviewer-0.8.1.dist-info/RECORD
