Metadata-Version: 2.1
Name: glyphviewer
Version: 0.8.1
Summary: A Django app for examining web fonts and the characters they contain.
Home-page: http://pypi.python.org/pypi/glyphviewer/
Author: Peter Murphy
Author-email: peterkmurphy@gmail.com
License: LICENSE.txt
Keywords: font glyph web woff ttf otf TrueType OpenType Django
Platform: UNKNOWN
Classifier: Development Status :: 4 - Beta
Classifier: Environment :: Other Environment
Classifier: Environment :: Web Environment
Classifier: Framework :: Django
Classifier: Intended Audience :: Developers
Classifier: Intended Audience :: Education
Classifier: Intended Audience :: End Users/Desktop
Classifier: Intended Audience :: Other Audience
Classifier: License :: OSI Approved :: GNU General Public License v3 (GPLv3)
Classifier: Programming Language :: Python
Classifier: Programming Language :: Python :: 2
Classifier: Operating System :: OS Independent
Classifier: Operating System :: MacOS
Classifier: Operating System :: Microsoft :: Windows
Classifier: Operating System :: POSIX
Classifier: Topic :: Artistic Software
Classifier: Topic :: Education
Classifier: Topic :: System :: Console Fonts
Classifier: Topic :: Text Processing :: Fonts
Classifier: Topic :: Text Processing :: Linguistic
Classifier: Topic :: Utilities
Requires-Dist: Django (>=1.0)
Requires-Dist: fonttools (>=3.0)
Requires-Dist: numpy (>=1.0)
Requires-Dist: brotli
Requires-Dist: chardet
